cortex_shell/__init__.py
cortex_shell/__main__.py
cortex_shell/application.py
cortex_shell/cache.py
cortex_shell/client/__init__.py
cortex_shell/client/base_client.py
cortex_shell/client/chatgpt_client.py
cortex_shell/client/iclient.py
cortex_shell/configuration/__init__.py
cortex_shell/configuration/config.py
cortex_shell/configuration/schema.py
cortex_shell/configuration/validator.py
cortex_shell/constants.py
cortex_shell/error_handler.py
cortex_shell/errors.py
cortex_shell/handlers/__init__.py
cortex_shell/handlers/default_handler.py
cortex_shell/handlers/ihandler.py
cortex_shell/handlers/repl_handler.py
cortex_shell/history/__init__.py
cortex_shell/history/ihistory.py
cortex_shell/history/persistent_history.py
cortex_shell/history/volatile_history.py
cortex_shell/post_processing/__init__.py
cortex_shell/post_processing/file_output_post_processing.py
cortex_shell/post_processing/ipost_processing.py
cortex_shell/post_processing/no_post_processing.py
cortex_shell/post_processing/shell_execution_post_processing.py
cortex_shell/processing/__init__.py
cortex_shell/processing/default_processing.py
cortex_shell/processing/file_processing.py
cortex_shell/processing/iprocessing.py
cortex_shell/renderer/__init__.py
cortex_shell/renderer/formatted_renderer.py
cortex_shell/renderer/irenderer.py
cortex_shell/renderer/plain_renderer.py
cortex_shell/resources/__init__.py
cortex_shell/resources/shell_integrations/__init__.py
cortex_shell/resources/shell_integrations/bash
cortex_shell/resources/shell_integrations/fish
cortex_shell/resources/shell_integrations/powershell
cortex_shell/resources/shell_integrations/pwsh
cortex_shell/resources/shell_integrations/zsh
cortex_shell/role.py
cortex_shell/session/__init__.py
cortex_shell/session/chat_session.py
cortex_shell/session/chat_session_manager.py
cortex_shell/types/__init__.py
cortex_shell/types/prompt_toolkit.py
cortex_shell/util.py
cortex_shell/yaml.py
cortex_shell-0.1.11.dist-info/LICENSE
cortex_shell-0.1.11.dist-info/METADATA
cortex_shell-0.1.11.dist-info/WHEEL
cortex_shell-0.1.11.dist-info/entry_points.txt
cortex_shell-0.1.11.dist-info/RECORD
