Metadata-Version: 2.1
Name: cortex-shell
Version: 0.1.11
Summary: A command-line productivity tool powered by AI models, will help you accomplish your tasks faster and more efficiently.
Home-page: https://github.com/frostbyte-ninja/cortex-shell
License: MIT
Keywords: bash,chatgpt,cli,gpt,openai,productivity,python,shell,terminal
Author: frostbyte-ninja
Requires-Python: >=3.9,<4.0
Classifier: Intended Audience :: Developers
Classifier: Intended Audience :: Information Technology
Classifier: Intended Audience :: System Administrators
Classifier: License :: OSI Approved :: MIT License
Classifier: Operating System :: OS Independent
Classifier: Programming Language :: Python :: 3
Classifier: Programming Language :: Python :: 3.9
Classifier: Programming Language :: Python :: 3.10
Classifier: Programming Language :: Python :: 3.11
Classifier: Programming Language :: Python :: 3.12
Classifier: Programming Language :: Python :: 3 :: Only
Classifier: Topic :: Software Development
Requires-Dist: click (>=8.1.3,<9.0.0)
Requires-Dist: distro (>=1.9.0,<2.0.0)
Requires-Dist: eval-type-backport (>=0.2.0,<0.3.0) ; python_version < "3.10"
Requires-Dist: identify (>=2.5,<3.0)
Requires-Dist: openai (>=1.13.4,<2.0.0)
Requires-Dist: pathvalidate (>=3.2,<4.0)
Requires-Dist: prompt-toolkit (>=3.0.43,<4.0.0)
Requires-Dist: pydantic (>=2.6.0,<3.0.0)
Requires-Dist: rich (>=13.1.0,<14.0.0)
Requires-Dist: ruamel-yaml (>=0.18.5,<0.19.0)
Requires-Dist: shellingham (>=1.5.0,<2.0.0)
Requires-Dist: typer (>=0.12.0,<0.13.0)
Requires-Dist: typing-extensions (>=4.9.0,<5.0.0)
Requires-Dist: validators (>=0.28.0,<0.29.0)
Project-URL: Repository, https://github.com/frostbyte-ninja/cortex-shell
